{"type":"Topology","bbox":[-84.641953,31.078400000000002,-83.649384,31.967456],"transform":{"scale":[0.00000992578925789261,0.00000889064890648903],"translate":[-84.641953,31.078400000000002]},"objects":{"tracts":{"type":"GeometryCollection","geometries":[{"type":"Polygon","arcs":[[0,1,2,3]],"properties":{"geo_id":"13007960100"}},{"type":"Polygon","arcs":[[4,5,6,7,8,9,10]],"properties":{"geo_id":"13095000400"}},{"type":"Polygon","arcs":[[11,-10,12,13,14,15]],"properties":{"geo_id":"13095000502"}},{"type":"Polygon","arcs":[[16,17,18,19,20,21]],"properties":{"geo_id":"13095011400"}},{"type":"Polygon","arcs":[[22,23]],"properties":{"geo_id":"13273120300"}},{"type":"Polygon","arcs":[[24,25,26,27]],"properties":{"geo_id":"13095000100"}},{"type":"Polygon","arcs":[[28,29,30,-28,31,-19]],"properties":{"geo_id":"13095000200"}},{"type":"Polygon","arcs":[[-15,32,33,34]],"properties":{"geo_id":"13095001000"}},{"type":"Polygon","arcs":[[35,36,-5,37,38,39]],"properties":{"geo_id":"13177020403"}},{"type":"Polygon","arcs":[[-8,40,41,42,43]],"properties":{"geo_id":"13095000700"}},{"type":"Polygon","arcs":[[-34,44,-22,45,46,47,48]],"properties":{"geo_id":"13095001100"}},{"type":"Polygon","arcs":[[-42,49,-29,-18,50]],"properties":{"geo_id":"13095000800"}},{"type":"Polygon","arcs":[[51,52,53,54]],"properties":{"geo_id":"13177020200"}},{"type":"Polygon","arcs":[[-21,55,-46]],"properties":{"geo_id":"13095001500"}},{"type":"Polygon","arcs":[[-38,-11,-12,56,57,58]],"properties":{"geo_id":"13095010401"}},{"type":"Polygon","arcs":[[-48,59,60,61]],"properties":{"geo_id":"13095010500"}},{"type":"Polygon","arcs":[[62,63,64]],"properties":{"geo_id":"13095010601"}},{"type":"Polygon","arcs":[[-32,-27,65,66,67,-64,68]],"properties":{"geo_id":"13095010700"}},{"type":"Polygon","arcs":[[-67,69,70,71]],"properties":{"geo_id":"13095010900"}},{"type":"Polygon","arcs":[[72,73,74,75,76,77,-25,78]],"properties":{"geo_id":"13095011200"}},{"type":"Polygon","arcs":[[79,80,81,-75,82]],"properties":{"geo_id":"13321950100"}},{"type":"Polygon","arcs":[[-16,83,-57]],"properties":{"geo_id":"13095000501"}},{"type":"Polygon","arcs":[[-14,84,-43,-51,-17,-45,-33]],"properties":{"geo_id":"13095000900"}},{"type":"Polygon","arcs":[[-56,-20,-69,-63,85,-60,-47]],"properties":{"geo_id":"13095001403"}},{"type":"Polygon","arcs":[[-82,86,87,-76]],"properties":{"geo_id":"13321950200"}},{"type":"Polygon","arcs":[[-54,88,89,-24,90,91]],"properties":{"geo_id":"13273120200"}},{"type":"Polygon","arcs":[[-91,-23,92,93]],"properties":{"geo_id":"13273120400"}},{"type":"Polygon","arcs":[[94,-52,95,-83,-74,96,97]],"properties":{"geo_id":"13177020100"}},{"type":"MultiPolygon","arcs":[[[-89,-53,-95,98,-36,99,100]],[[101]]],"properties":{"geo_id":"13177020300"}},{"type":"Polygon","arcs":[[-98,102,-6,-37,-99]],"properties":{"geo_id":"13177020402"}},{"type":"Polygon","arcs":[[-87,-81,103,104,105]],"properties":{"geo_id":"13321950400"}},{"type":"Polygon","arcs":[[106,107,-105,108]],"properties":{"geo_id":"13321950600"}},{"type":"Polygon","arcs":[[-90,-101,-100,-40,109,-93],[-102]],"properties":{"geo_id":"13273120500"}},{"type":"Polygon","arcs":[[-4,110]],"properties":{"geo_id":"13007960200"}},{"type":"Polygon","arcs":[[-79,-31,111]],"properties":{"geo_id":"13095010302"}},{"type":"Polygon","arcs":[[-110,-39,-59,112,-49,-62,113,-1,114]],"properties":{"geo_id":"13095010403"}},{"type":"Polygon","arcs":[[-61,-86,-65,-68,-72,115,116,-2,-114]],"properties":{"geo_id":"13095010602"}},{"type":"Polygon","arcs":[[-71,117,118,-116]],"properties":{"geo_id":"13095011000"}},{"type":"Polygon","arcs":[[-66,-26,-78,119,-107,120,-118,-70]],"properties":{"geo_id":"13095011600"}},{"type":"Polygon","arcs":[[-58,-84,-35,-113]],"properties":{"geo_id":"13095010402"}},{"type":"Polygon","arcs":[[-103,-97,-73,-112,-30,-50,-41,-7]],"properties":{"geo_id":"13095011300"}},{"type":"Polygon","arcs":[[-77,-88,-106,-108,-120]],"properties":{"geo_id":"13321950500"}},{"type":"Polygon","arcs":[[-9,-44,-85,-13]],"properties":{"geo_id":"13095000600"}}],"bbox":[-84.641953,31.078400000000002,-83.649384,31.967456]}},"arcs":[[[21366,40296],[558,8],[7236,-80],[537,33],[7264,-27]],[[36961,40230],[6397,-24],[47,514],[184,5],[6714,-22],[154,-11]],[[50457,40692],[-95,-125],[121,-584],[-102,-228],[-207,-257],[-198,-163],[-323,-533],[-206,-722],[-250,-384],[-200,109],[-119,209],[-148,75],[-450,-254],[-356,-132],[-850,-209],[-243,-124],[-173,-213],[-52,-195],[47,-237],[224,-391],[80,-385],[-23,-221],[-150,-318],[-277,-284],[-183,58],[-35,194],[119,483],[-125,220],[-1208,-743],[-113,-133],[-12,-265],[-329,-407],[-31,-117],[-24,-661],[-73,-121],[-30,-307],[69,-249],[25,-323],[188,-488],[-25,-336],[9,-536],[-306,-221],[-133,159],[-263,162],[-234,-34],[-182,118],[-148,14],[-76,-119],[22,-194],[-91,-82],[-293,63],[-117,112],[-127,-60],[-534,-38],[-251,-47],[-44,-68],[-81,-445],[-221,-448],[-225,-162],[-160,-212],[-91,-306],[-99,-116],[-319,-52],[-272,-177],[-162,26],[-106,151],[17,167],[-87,112],[-119,-39],[-43,-207],[-106,-139],[-282,-158],[-284,-56],[-268,-175],[-133,128],[-137,305],[-348,-7],[-380,168],[-317,89],[-394,-409],[-15,-171],[173,-272],[-35,-142],[-550,-338],[-232,-63],[-103,127],[-166,-18],[-236,-285],[-117,-24],[-223,266],[-90,-114],[-112,-299],[-248,-118],[-234,95],[-347,17],[-281,-48],[-163,-128],[-270,-81],[-408,77],[-321,-51],[-116,-69],[-133,-208],[61,-276],[-62,-534],[-68,-136],[-230,-166],[-219,-46],[-275,36],[-273,262],[-266,-79],[-535,-176],[-911,-758],[46,-121],[330,-434],[108,-409],[59,-545],[-79,-117],[-45,-259],[-413,-312],[-36,-339],[53,-411],[-165,-274],[-250,-213],[-312,-484],[-152,-67],[-101,-128],[-172,-61],[-221,-183],[-200,-374],[-318,-350],[-2,-327],[41,-314],[-300,-261],[-130,-258],[-98,-332],[-44,-371],[-103,-306],[-84,-77],[-531,-157],[-315,127],[-316,-153],[-197,-154],[-69,-179],[-152,-126],[-317,-44],[-202,-80],[-449,-329],[-232,-70],[55,-134],[-47,-261],[-231,-169],[-347,-64],[-205,-145],[-413,-412],[-1,-454],[34,-181],[-65,-184],[-171,-78],[-108,-155],[183,-304],[151,-86],[201,-374],[-60,-404],[-106,-66],[-143,-241],[-120,-301],[-387,-190],[-101,-408],[-300,-213],[-299,-82],[-129,159],[185,277],[135,391],[-39,224],[-184,243],[-106,32],[13,-214],[-125,-171],[-388,-283],[-86,-132],[-206,-100],[-215,128],[-362,-225],[-584,-664],[-193,-115],[-334,-67],[-250,2],[-143,-119],[-482,-937],[-421,-495],[-290,-145],[-210,64],[-385,211],[-188,55]],[[17495,10199],[74,182],[-472,599],[-92,180],[74,85],[-182,496],[3,316],[170,327],[0,162],[-79,155],[138,143],[-146,215],[123,366],[269,49],[178,113],[-223,122],[-92,150],[-155,38],[-182,148],[-26,193],[239,62],[-39,344],[-102,-11],[-159,-142],[-77,68],[-4,212],[211,281],[51,230],[219,157],[8,107],[161,3],[47,102],[-144,184],[48,243],[153,121],[26,146],[257,132],[178,-40],[96,317],[-99,368],[-92,252],[140,-56],[44,3],[-4,74],[-24,40],[-59,22],[-158,-20],[-135,137],[-92,257],[99,109],[2,363],[318,100],[-166,232],[-377,282],[155,142],[-147,142],[122,355],[-124,299],[179,150],[-695,541],[-36,115],[-158,37],[-41,-182],[-115,77],[-45,193],[-297,-61],[104,-174],[-107,-40],[-293,297],[-294,415],[22,174],[-161,42],[-73,395],[-147,512],[-640,155],[80,353],[-100,199],[88,161],[442,-52],[346,-89],[52,125],[175,90],[-10,125],[-235,168],[-298,135],[-81,170],[303,259],[230,335],[264,140],[-431,720],[226,282],[195,172],[-68,166],[-23,348],[-190,205],[1,196],[319,66],[-117,301],[78,289],[55,659],[-164,161],[77,186],[299,19],[148,116],[-14,132],[190,62],[59,134],[-134,255],[48,151],[-55,235],[-214,212],[-218,80],[55,136],[-258,330],[128,107],[152,276],[107,222],[-127,145],[179,416],[186,113],[-57,91],[184,92],[-25,145],[-134,110],[-5,125],[324,353],[113,-16],[7,392],[110,49],[-88,242],[38,340],[-118,71],[171,282],[168,60],[0,107],[166,-116],[176,217],[146,306],[118,60],[-38,171],[102,191],[-78,209],[123,288],[259,46],[111,163],[-123,125],[-36,185],[155,761],[239,122],[227,281],[397,17],[142,78],[48,303],[261,215],[12,165],[149,113],[30,404],[277,169],[137,284],[2,308],[146,363],[153,232],[134,35],[90,377],[91,-86],[201,34],[12,161],[103,71],[305,14],[46,75]],[[41468,61194],[1133,13],[2661,6],[455,8]],[[45717,61221],[742,-14],[386,24]],[[46845,61231],[116,-1368]],[[46961,59863],[0,-644]],[[46961,59219],[-949,10],[-331,3],[-527,5],[-140,68],[-1187,31]],[[43827,59336],[-451,481],[-449,367]],[[42927,60184],[-976,762],[-483,248]],[[42215,60189],[712,-5]],[[43827,59336],[264,-292],[291,-319],[659,-602],[370,-409],[765,-118]],[[46176,57596],[-19,-300],[-275,-412],[-58,-332]],[[45824,56552],[-152,20],[-758,-6],[-382,26],[-635,413],[-188,61],[-78,8],[-1053,-9]],[[42578,57065],[-13,1549],[-69,313],[-258,768],[-23,494]],[[46916,56344],[769,247],[260,13]],[[47945,56604],[713,-12],[-2,173],[763,2],[1,-165],[239,258],[64,-473],[191,-119]],[[49914,56268],[-78,-196],[-28,-163]],[[49808,55909],[-384,-5],[0,-181],[-762,-1]],[[48662,55722],[-1,179],[-722,-1],[-2,-699],[-157,-119],[-866,-4]],[[46914,55078],[2,1266]],[[23945,78388],[-785,-49],[-1128,-162],[-1219,-3],[-1147,22],[-901,37],[-701,-35],[-430,-35],[-242,78],[-309,326],[-149,105],[-791,471],[-270,104],[-1015,308],[-360,58],[-628,19],[-279,109],[-260,274],[-436,404],[-751,779]],[[12144,81198],[296,-2],[178,142],[148,351],[-65,343],[145,314],[-4,153],[204,108],[249,371],[215,87],[274,-32],[100,149],[438,288],[-5,106],[141,286],[311,152],[19,167],[401,464],[57,174],[-14,411],[268,515],[41,207],[347,304],[60,153],[145,40],[129,260],[38,199],[289,17],[113,158],[189,-205],[210,-404],[588,-1309],[192,-3],[607,-275],[792,-126],[244,-91],[513,-314],[281,-46],[102,26],[289,484],[349,432],[844,-260],[948,-354],[446,-51],[512,1],[-106,-2835],[-1169,-806],[278,-102],[228,-493],[361,-221],[264,-275],[353,-29],[152,-130],[43,-178],[-92,-422],[-91,-57],[107,-168],[-151,-484]],[[53424,56397],[2388,14],[809,860],[667,389],[27,-1726],[-41,-204],[4,-1012],[-163,-12],[-319,-336],[130,-111]],[[56926,54259],[-593,23],[-1205,87]],[[55128,54369],[-1870,204]],[[53258,54573],[199,912],[13,116],[-14,384],[-32,412]],[[49914,56268],[71,271],[81,1002]],[[50066,57541],[131,518]],[[50197,58059],[625,-314],[473,-666],[235,-322],[373,-35],[1,-72],[1088,14],[46,-259],[386,-8]],[[53258,54573],[-294,155],[-219,324],[-270,515],[-583,3],[-529,107],[-1024,250],[-531,-18]],[[45824,56552],[13,-544]],[[45837,56008],[-3609,-1126]],[[42228,54882],[73,262],[260,987],[17,934]],[[34783,65349],[491,32],[327,60],[857,431],[913,-851],[386,-193],[153,-42],[281,-244],[177,6],[193,195],[164,-17],[139,-147],[290,-51],[287,100],[294,-17],[38,-114],[510,-256],[284,-44],[287,88],[376,42],[192,60],[254,-50],[599,-59],[367,112],[457,62],[377,104],[531,-57],[441,-81],[365,-165]],[[44813,64253],[31,-384],[161,-562],[300,-1405],[412,-681]],[[41468,61194],[-1402,-17],[-719,30],[-974,-17],[-2823,-52]],[[35550,61138],[-877,-1]],[[34673,61137],[110,4212]],[[46961,59863],[1514,-1881],[176,-310],[1,-103]],[[48652,57569],[-755,3],[-133,-156]],[[47764,57416],[-126,133],[-700,19]],[[46938,57568],[23,1651]],[[45837,56008],[1079,336]],[[46914,55078],[-23,-1023]],[[46891,54055],[-27,-1121]],[[46864,52934],[-3250,3],[12,503],[30,1327],[-720,-236],[-285,-53],[-517,62]],[[42134,54540],[94,342]],[[48652,57569],[1,-154],[299,0],[-1,154],[1115,-28]],[[47945,56604],[0,160],[-177,0],[-78,240],[74,412]],[[56140,93987],[470,-2580],[33,-134],[71,-193],[744,-1525],[99,-269],[16,-413],[-103,-335],[-611,-874],[-1545,-1701],[-103,-124],[-2050,-3149],[-554,-1052],[-1946,-3141]],[[50661,78497],[-294,110],[-47,298],[-133,142],[12,259],[-131,4],[-55,231],[-116,186],[-236,123],[-56,197],[191,255],[-185,134],[-278,64],[-84,334],[-147,159],[42,135],[-333,400],[-226,65],[8,99],[-250,15],[-156,167],[-170,41],[-58,252],[-183,90],[-89,166],[-328,231],[-13,-334],[219,-846],[7,-511],[-973,6],[-382,31],[-109,109],[-218,383],[-378,738],[-50,48],[-1069,501],[-366,249],[-837,470],[-208,322],[-1222,11],[-732,34],[-16,329],[-238,449],[-105,62],[-848,257],[-58,340],[-263,264],[-362,129],[-213,-339],[-265,-193],[-53,-100],[-437,-154],[-69,-157]],[[38101,84752],[-111,243],[-148,59],[-155,170],[-526,233],[164,102],[-609,300],[82,108],[-82,233],[78,429],[-9,225],[-482,64],[-293,445],[-180,-4],[-158,105],[29,114],[-242,-1],[-105,339],[-255,21],[90,266],[-161,198],[115,61],[-144,55],[-22,-116],[-209,101],[-39,96],[-225,68],[-44,100],[-116,-63],[-194,105],[-159,-4],[-83,99],[-394,-47],[-88,186],[-122,-140],[-191,11],[-172,-85],[-332,190],[0,76],[-324,122],[-333,-66],[-231,221],[-147,-114],[-57,97],[-254,138],[-368,-88],[-297,37]],[[30598,89441],[-32,177],[101,2776],[-106,-2],[47,1841],[5170,-85],[20,56],[2186,13],[870,-28],[5464,-86],[1101,-14],[10721,-102]],[[48662,55722],[3,-772],[-71,-76],[-93,-102],[-477,-644],[-46,-65],[-544,-3],[-543,-5]],[[42215,60189],[-1281,0],[-6,-1121],[3,-587],[13,-86],[39,-204],[-232,-679],[-14,-456]],[[40737,57056],[-1374,4],[-3042,0]],[[36321,57060],[683,2953],[-254,-156],[-162,-31],[-723,71],[-358,3],[54,329],[-11,909]],[[46864,52934],[190,-1]],[[47054,52933],[-119,-146],[-445,-749],[-1428,-2108],[-722,-1027],[-4134,-4887]],[[40206,44016],[90,3883],[144,248],[491,722],[535,707],[227,399],[749,693],[366,477],[-469,434],[-143,358],[-172,1797],[-3,269],[113,537]],[[47517,52966],[630,273],[892,104],[346,24],[566,-38]],[[49951,53329],[3,-227],[480,-873],[73,-259]],[[50507,51970],[-1386,-7],[-359,176],[-291,4],[-929,-1],[6,362],[144,438],[-175,24]],[[55128,54369],[28,-857],[-11,-389],[-131,-376],[-1605,-385],[-313,211],[-4,-287]],[[53092,52286],[-663,-162],[-123,5],[-239,161],[-112,26],[-1004,-471],[-295,-144],[-49,-46]],[[50607,51655],[-100,315]],[[49951,53329],[20,140],[-191,235],[404,113],[56,346],[-175,672],[-203,570],[-54,504]],[[53092,52286],[-50,-1577],[1,-1405]],[[53043,49304],[5,-2090],[-889,12],[-381,-133],[-102,-1322],[-778,-20],[6,-1020],[-1653,-26]],[[49251,44705],[-13,524],[31,332],[319,317],[97,152],[0,581],[-50,275],[175,615],[10,159],[-179,255],[-343,665],[1,221],[176,309],[280,265],[239,41],[348,168],[119,136],[17,411],[246,833],[24,287],[-141,404]],[[54075,59655],[-9,450],[298,285],[18,329],[239,93],[496,-341],[262,-326],[134,-293],[511,-338],[171,-28],[1009,422],[243,193],[42,226],[405,81],[422,-793],[162,71],[107,464],[124,170],[251,204],[348,389],[400,245],[415,37],[199,125]],[[60322,61320],[286,1224],[54,100],[272,168],[118,195],[85,346],[107,176],[122,56],[205,-100],[118,214],[-16,285],[90,124],[725,186],[261,-29],[72,58]],[[62821,64323],[2522,-27],[-9,-969],[-949,32],[-18,-907],[-952,-2],[-19,-1016],[1657,64]],[[65053,61498],[-57,-3064],[40,-831],[-15,-3038],[1507,-22],[-6,-1129]],[[66522,53414],[-1,-188],[-1510,6]],[[65011,53232],[-31,275],[-1623,147],[-6416,592],[-15,13]],[[53424,56397],[-58,424],[-150,319],[202,25],[606,254],[43,40],[4,794],[-4,685],[63,82],[-55,635]],[[70777,86555],[183,-338],[525,-11],[465,105],[320,293],[892,-180],[146,44],[233,-65],[566,-277],[335,-234],[321,2],[196,-152],[420,67],[206,-25],[403,-174],[547,-129],[251,-156],[135,49],[322,-27],[69,84],[176,-58],[37,91],[179,-29],[149,-141],[143,46],[465,9],[263,-88],[253,66],[125,-126],[116,106],[32,-460],[1,-1449],[984,-15],[22,440],[-14,890],[158,-501],[406,-195],[35,-190],[410,-268],[-63,-438],[59,-172],[247,-216],[372,-110],[153,-324],[165,-36],[173,181],[330,117],[380,13],[282,-205],[154,-377],[158,-174],[408,-195],[268,50],[212,-107],[408,-289],[-35,-2487],[-45,-2033],[218,-8],[15,-3579],[-16,-420],[27,-309],[8,-6009],[22,-467],[-47,-4465],[38,-253],[1004,-13]],[[86147,61234],[104,-206],[-35,-1026]],[[86216,60002],[-648,-495],[-709,430],[-252,197],[-506,679],[-335,360],[-120,74],[-119,24],[-4515,62],[-226,22],[-530,-11],[-13203,154]],[[62821,64323],[182,139],[77,182],[-18,212],[96,250],[-67,211],[34,130],[244,194],[57,118],[-429,850],[-106,643],[-115,238],[-229,353],[-94,252],[0,206],[154,322],[93,448],[-260,646],[-189,242],[-49,224],[38,304],[-146,556],[-229,263],[-361,145],[-141,188],[19,107],[441,346],[543,178],[167,86],[272,333],[308,816],[337,342],[402,-11],[63,146],[-30,440],[63,314],[250,467],[65,356],[-44,244],[104,254],[442,304],[534,-4],[165,100],[191,370],[239,224],[152,224],[22,236],[-45,239],[-127,194],[-399,365],[-227,320],[29,259],[227,449],[-4,126],[-188,121],[-242,52],[-407,15],[-244,125],[-575,523],[-103,211],[-20,237],[35,482],[254,359],[360,49],[728,-73],[210,4],[303,312],[236,55],[415,-89],[418,-286],[302,-22],[54,280],[-53,142],[-296,264],[6,340],[188,217],[89,527],[232,345],[102,239],[105,390],[352,445],[182,315],[226,64],[500,-81],[106,14],[126,215],[33,335],[66,89],[311,99],[418,312],[120,143],[95,379],[167,120],[158,1],[312,-155],[174,-22]],[[42578,57065],[-1841,-9]],[[46176,57596],[195,-26],[567,-2]],[[47517,52966],[-463,-33]],[[86216,60002],[-52,-335],[-6,-1341],[-130,-587],[-7,-162],[202,-1141],[-534,-358],[-166,-156],[-550,-670],[-152,-142],[-724,-568],[-160,-165],[-130,-202],[-348,-684],[249,-784],[116,-175],[193,-110],[-39,-140],[147,-295],[-24,-208],[108,-73],[176,-316],[23,-357],[110,-300],[-77,-88],[-33,-140],[-839,-7]],[[83569,50498],[-559,9],[-822,283],[-98,16],[-2401,136],[-199,75],[-835,413],[-614,363],[-924,297],[-468,213],[-465,349],[-219,135],[-351,141],[-268,58],[-2558,216],[-2060,31],[-1030,102],[-232,-23],[-929,-202],[-597,-9],[-1418,313]],[[38101,84752],[143,-384],[276,-70],[-1,-112],[-240,-264],[-162,-74],[40,-267],[39,-99],[93,-129],[-189,-105],[186,-182],[-105,-93],[104,-95],[-74,-195],[-108,7],[-74,-131],[146,-181],[-47,-275],[191,-65],[91,-517],[-39,-272],[-92,-12],[-75,-215],[100,-115],[-127,-71],[267,-306],[-106,-166],[27,-183],[230,44],[37,-100],[-2817,47],[-57,-3721]],[[35758,76451],[-3651,40],[-466,101],[-1390,485],[-366,103],[-1525,299],[-541,34],[-568,-50],[-361,3],[-986,126],[-362,131],[-967,495],[-165,67],[-465,103]],[[12144,81198],[-129,-63],[-203,122],[-83,-33],[-16,-158],[-263,-188],[-285,-415],[-245,140],[-148,12],[-268,-235],[-272,-76],[-120,-91],[-22,-125],[-286,-284],[-158,-32],[-40,-107],[-342,-191],[-130,-152],[-157,4],[-318,-224],[-370,-79],[-168,-193],[-7,-160],[-146,-169],[67,-255],[86,-230],[-183,-158]],[[7938,77858],[-4022,157],[27,978],[-5,369],[234,10417],[77,4901],[5512,-80],[363,22],[3855,-24],[766,15],[433,-45],[3827,6],[19,801],[794,-24],[145,4648],[73,-223],[102,23],[166,-312],[-11,-343],[68,-68],[171,102],[119,-45],[64,-205],[59,60],[97,-481],[92,-67],[133,55],[61,-290],[246,29],[118,-261],[367,-187],[105,-212],[187,-28],[-18,-184],[96,-125],[455,-275],[77,-104],[415,-346],[167,31],[78,98],[191,-164],[410,-145],[-9,-116],[322,-459],[168,-95],[29,-365],[167,-37],[239,-242],[347,-143],[122,-177],[376,-295],[240,-86],[100,-243],[133,-92],[-12,-275],[166,-57],[-103,-197],[11,-104],[246,-198],[135,-37],[125,-173],[37,-249],[155,-200],[230,-198],[198,-54],[30,-155],[126,-90],[72,57],[234,-114],[35,-292],[263,-161],[67,-199],[221,-204],[19,-224],[106,-116],[136,72],[104,-110],[230,-103],[90,-302],[271,113],[105,-76],[-51,-141],[166,-156],[-12,-141],[222,-60],[129,-125],[37,-170],[266,-106],[53,-84],[206,88]],[[23945,78388],[24,-191],[-99,-11],[-62,-223],[36,-405],[94,-60],[60,-323],[146,-411],[68,-123],[210,-60],[145,-181],[-9,-248],[186,-324],[251,-216],[436,-206],[276,-5],[60,-263],[202,-176],[-5,-253],[99,-266],[286,-267],[3,-336],[129,-335],[66,-382],[129,-318],[-15,-243],[-121,-134],[-61,-382],[52,-70],[-79,-311],[-225,-299],[-249,-158],[-72,-169],[-174,-95],[-67,-198],[-227,-361],[-416,-352],[-138,-47],[-80,-310],[-245,-209],[-142,-253],[-174,-78],[-246,-244],[-301,-168],[-213,-594],[-242,-232],[-30,-238],[39,-217],[-116,-60],[-52,-375],[-359,-374],[-257,-5],[-95,-126],[56,-102],[-212,-313],[-317,-206],[-73,-215],[-113,-55],[-133,-328],[-195,-157],[-43,-206],[-175,-142],[-22,-140],[-221,-331],[-119,-5],[-541,-482],[-141,-178],[-22,-303],[-67,-129],[-88,-562],[-290,-496],[12,-165],[-90,-227],[-136,-165],[-142,-468]],[[19299,61128],[-2,-69],[-9716,-6],[225,244],[-71,82],[3,271],[167,9],[47,385],[112,236],[67,393],[252,215],[29,132],[-127,138],[378,695],[-150,384],[29,286],[-77,11],[-55,666],[130,238],[-269,409],[-21,260],[237,181],[-60,336],[99,179],[-123,210],[204,219],[125,40],[34,284],[-44,316],[-138,118],[-91,347],[-287,335],[50,175],[-95,145],[80,96],[-443,550],[-54,451],[-207,329],[-6,563],[-60,141],[108,191],[-106,136],[-118,53],[-5,184],[-230,150],[-44,212],[-244,113],[-69,133],[13,218],[-128,85],[-30,175],[64,251],[-83,5],[-111,268],[-324,304],[-146,412],[20,253],[-86,48],[-81,388],[92,335],[-179,128],[-108,253],[60,313],[-188,77],[-125,270],[-206,234],[86,72],[-87,356],[114,186],[354,329],[80,369],[174,235]],[[54186,66999],[617,404],[-121,194],[127,131],[-257,52],[-112,181],[59,115],[-263,9],[-168,88],[127,246],[-67,251],[66,319],[-348,129],[-220,514],[-101,446],[140,481],[-88,120],[57,148],[-164,261],[41,87],[-204,207],[-53,173],[-158,-26],[-27,150],[-184,105],[-102,821],[-283,68],[-435,246],[-95,144],[118,280],[-23,110],[299,630],[-26,113],[-268,152],[-120,709],[-261,247],[-64,135],[-201,36],[-78,293],[42,319],[-62,215],[70,256],[-128,139],[39,298],[-71,203],[-167,151],[118,24],[-35,180],[87,105],[-92,70],[181,105],[51,203],[-112,170],[-606,291]],[[56140,93987],[4590,-30],[2860,-18],[1018,-78],[4414,-101],[100,12],[1926,-34],[107,5],[1329,-246],[-263,-448],[-230,-171],[-348,-393],[-119,-213],[-56,-359],[28,-199],[364,-780],[-34,-154],[-309,-97],[-138,-159],[-61,-206],[294,-495],[52,-204],[195,-374],[26,-253],[167,-430],[26,-279],[-120,-162],[-464,-294],[-236,-32],[-209,-103],[-107,-364],[-40,-598],[-125,-175]],[[60322,61320],[-3373,29],[-1483,-74],[-3627,-23],[-200,-11],[-1449,0]],[[50190,61241],[490,430],[-49,382],[216,135],[197,266],[208,88],[-17,489],[302,278],[175,-20],[168,249],[221,90],[276,-118],[27,138],[228,-10],[227,275],[92,-13],[49,173],[114,8],[277,-139],[51,220],[264,62],[-53,72],[238,225],[-78,79],[119,82],[10,228],[-99,79],[211,50],[-43,142],[97,198],[1,198],[372,182],[58,309],[-120,106],[215,93],[6,94],[-177,233],[-193,60],[-122,156],[137,0],[54,155],[-153,34]],[[54186,66999],[-457,47],[-1146,-6],[-225,95],[-267,-92],[-1900,0],[3,293],[-2012,32],[-464,84],[-440,125],[-295,-82],[-633,-337],[-299,-64],[-2092,13],[77,-259],[503,-1351],[222,-429],[127,-480],[-75,-335]],[[34783,65349],[80,3102],[27,451],[-963,8]],[[33927,68910],[28,807],[958,-15],[149,5229],[27,586],[655,42],[14,892]],[[33927,68910],[-1,-4],[-30,-883],[-917,0],[30,898],[918,-11]],[[50190,61241],[-241,11],[-2710,-42],[-10,8],[-384,13]],[[86147,61234],[6861,-88],[224,-234],[406,-88],[185,71],[74,-136],[350,56],[63,-247],[104,-109],[22,-282],[224,-435],[-13,-175],[101,-207],[179,-148],[87,-225],[99,-22],[26,231],[194,-58],[215,-158],[94,-309],[284,-231],[206,-56],[145,31],[197,-102],[119,38],[103,178],[-14,158],[468,80],[163,-131],[45,-236],[189,-245],[207,-83],[170,49],[119,-335],[-70,-78],[161,-311],[-84,-83],[105,-235],[-501,-467],[31,-382],[-35,-240],[117,-233],[13,-257],[407,-467],[364,-231],[267,28],[155,112],[29,210],[270,101],[254,161],[174,-180],[299,-167],[-20,-762],[5,-733],[-110,-7868],[-1527,45],[-46,-3359],[-43,-2374],[1501,-28],[-110,-4750],[-22,-1763],[-10,-65],[-58,-3530],[-34,-1506],[-6023,111],[-10,-632]],[[93492,27853],[-228,209],[-479,175],[-231,188],[-119,169],[-276,-16],[-265,169],[-335,-31],[-176,70],[-119,229],[71,109],[-118,119],[-84,539],[-173,190],[-295,153],[-93,381],[-321,298],[-211,48],[-234,199],[-255,331],[-309,164],[-265,29],[-97,132],[-297,20],[-434,230],[-115,0],[-220,219],[-389,30],[-116,56],[-124,233],[-248,327],[-283,179],[-153,261],[-234,244],[-14,495],[-58,180],[81,103],[-302,159],[-90,101],[-388,146],[-163,151],[-490,228],[-27,324],[-117,209],[-494,443],[-195,-30],[-450,131],[-109,235],[-195,99],[-147,172],[-54,198],[-341,278],[-163,506],[-112,212],[-25,210],[-137,88],[-231,541],[-44,287],[-132,-13],[-55,155],[-201,243],[-12,371],[-250,243],[-143,66],[-86,233],[18,147],[-108,177],[-524,371],[-278,323],[-99,366]],[[80132,41654],[44,374],[189,97],[127,218],[-14,395],[-181,312],[-55,203],[-173,184],[32,248],[229,17],[313,266],[-20,111],[107,204],[-14,258],[203,251],[42,248],[-108,180],[-266,235],[-122,226],[18,409],[-238,238],[274,146],[433,55],[653,189],[-23,118],[1429,506],[774,315],[415,138],[57,225],[405,16],[-807,527],[-293,241],[7,1653],[0,41]],[[64897,41094],[13,601],[-14,649],[13,889],[1522,80]],[[66431,43313],[661,-10],[1060,54],[200,-46],[192,-174],[555,-344],[153,-207],[112,-354],[125,-97],[285,-120],[1241,-421],[201,-248],[156,-449],[203,-309],[251,261],[75,148],[172,731],[1815,-18],[537,72],[462,-125],[647,44],[2210,-29],[199,241],[918,-48],[601,-188],[670,-23]],[[93492,27853],[-16,-862],[-4514,66],[-15,1493],[-1681,10],[-3820,40],[-5944,85],[-4836,56],[-1124,11],[-6809,106],[6,213],[158,12023]],[[34673,61137],[-15374,-9]],[[17495,10199],[-199,-53],[-88,-194],[227,-174],[40,-143],[-180,-112],[-296,-304],[-310,-166],[-445,-102],[-194,-144],[-67,-164],[53,-194],[171,-153],[230,-405],[7,-125],[-157,-359],[-71,-592],[-260,-153],[-289,230],[-235,-147],[-202,-256],[-199,-145],[-356,-351],[-130,-200],[-333,-277],[-414,-209],[-184,-253],[451,-245],[137,-128],[90,-230],[-61,-412],[-132,-257],[-372,-214],[-62,-126],[-53,-754],[30,-127],[215,-362],[14,-268],[-53,-232],[142,-491],[-175,-282],[-297,-926],[-3484,71],[215,8564],[38,1708],[247,5768],[-29,472],[33,1357],[-6,203],[54,1176],[8,649],[-5635,207],[-655,14],[-3749,101],[-43,19],[-454,1],[12,4171],[-40,583],[30,1267],[172,8],[27,1159],[127,1],[34,1034],[1058,5],[-10,1064],[-1065,12],[11,3211],[-138,22],[-18,903],[89,6],[124,6233],[7370,-184],[1791,-45],[30,95],[35,905],[1110,-46],[-35,-977],[1104,-23],[8,962],[1087,-48],[-25,-970],[1102,-70],[83,-268],[1126,-11],[-3,850],[890,-1],[3,386],[1344,-7],[-7,1054],[975,6],[-4,735],[1128,-2],[-24,-954],[1216,2],[1,-531],[-1217,-4],[-2,-552],[1839,5]],[[50197,58059],[92,158],[99,217],[260,300],[269,72],[273,382],[244,152],[363,395],[598,-25],[488,-142],[38,-121],[-84,-206],[160,-132],[547,140],[324,309],[207,97]],[[36321,57060],[-560,0],[-237,-918],[-759,-1035],[-739,-1122],[-655,-1310],[-250,-361],[-168,-337],[4209,1317],[2149,673],[2917,915]],[[40206,44016],[-3245,-3786]],[[21366,40296],[-1,126],[176,130],[-57,196],[146,191],[120,620],[233,88],[192,-33],[209,138],[35,144],[696,680],[-581,1428],[-558,2680],[-192,138],[0,327],[-351,240],[-114,494],[-238,375],[-522,219],[-117,357],[28,185],[-31,421],[-84,125],[31,304],[-68,265],[-130,139],[-4,265],[-287,408],[-24,367],[-253,575],[-100,88],[107,187],[-21,229],[-230,166],[-533,299],[-40,332],[-4,567],[110,163],[-44,265],[26,359],[174,415],[82,455],[-13,285],[-138,179],[-114,662],[-253,187],[-62,147],[79,279],[149,153],[111,212],[69,329],[237,251],[204,283],[-96,312],[67,222],[211,193],[40,133],[-32,210],[-212,448],[35,254],[-150,201],[83,93],[18,304],[-81,378]],[[49251,44705],[120,-493],[311,-345],[8,-316],[-58,-173],[-455,39],[-114,-139],[-22,-304],[-90,-304],[-2,-306],[100,-68],[238,19],[213,-171],[422,-427],[366,-193],[92,-132],[385,-186],[30,-233]],[[50795,40973],[-317,-255],[-21,-26]],[[53043,49304],[2317,-28],[193,-73],[424,-399],[212,-79],[861,0],[203,141],[359,576],[1160,-665],[-307,-558],[-23,-164],[32,-844],[-35,-904],[46,-1438],[-50,-406],[-21,-3445]],[[58414,41018],[-5417,-45],[-253,-22],[-1949,22]],[[65011,53232],[-4,-888],[-38,-4071],[-39,-3551],[1515,-22],[-14,-1387]],[[64897,41094],[-6483,-76]]]}
